Metadata-Version: 1.0
Name: bigrandomgraphs
Version: 0.0.2
Summary: Python package for fast creation of large random graphs
Home-page: UNKNOWN
Author: Jason P. Smith
Author-email: UNKNOWN
License: UNKNOWN
Platform: UNKNOWN
